django_task/__init__.py
django_task/apps.py
django_task/constants.py
django_task/handler.py
django_task/models.py
django_task/serializers.py
django_task/services.py
django_task/settings.py
django_task/urls.py
django_task/views.py
django_task/migrations/0001_initial.py
django_task/migrations/0002_rename_return_value_task_response_remove_task_args_and_more.py
django_task/migrations/0003_remove_task_error_reason.py
django_task/migrations/0004_task_task_name.py
django_task/migrations/0005_task_remark.py
django_task/migrations/0006_alter_task_task_name.py
django_task/migrations/__init__.py
django_bg_task-0.4.4.dist-info/METADATA
django_bg_task-0.4.4.dist-info/WHEEL
django_bg_task-0.4.4.dist-info/licenses/LICENSE
django_bg_task-0.4.4.dist-info/RECORD
