Metadata-Version: 2.4
Name: django-bg-task
Version: 0.4.4
Summary: A small Django DRF extension for managing background task with celery
Project-URL: Homepage, https://github.com/abhishm20/django-task
Project-URL: Bug Tracker, https://github.com/abhishm20/django-task/issues
Author-email: Abhishek Sharma <abhishm20@gmail.com>
License-File: LICENSE
Classifier: License :: OSI Approved :: MIT License
Classifier: Operating System :: OS Independent
Classifier: Programming Language :: Python :: 3
Requires-Python: >=3.7
